lowerated/__init__.py
lowerated/rate/__init__.py
lowerated/rate/entity.py
lowerated/rate/reviews_extraction.py
lowerated/rate/utils.py
lowerated-0.3.4.dist-info/LICENSE
lowerated-0.3.4.dist-info/METADATA
lowerated-0.3.4.dist-info/WHEEL
lowerated-0.3.4.dist-info/top_level.txt
lowerated-0.3.4.dist-info/RECORD
