Metadata-Version: 2.1
Name: lowerated
Version: 0.3.4
Summary: Lowerated is an opensource library that allows you to rate any item in a statistically accurate way
Home-page: http://lowerated.com/products/
Author: Muhammad Wisal
Author-email: wisal@lowerated.com
License-File: LICENSE
Requires-Dist: numpy
Requires-Dist: python-dotenv
Requires-Dist: websockets
Requires-Dist: fastapi
Requires-Dist: nltk
Requires-Dist: tqdm
Requires-Dist: beautifulsoup4
Provides-Extra: openai
Requires-Dist: openai; extra == "openai"
